sigmon/__init__.py
sigmon-0.0.0.dist-info/METADATA
sigmon-0.0.0.dist-info/WHEEL
sigmon-0.0.0.dist-info/top_level.txt
sigmon-0.0.0.dist-info/RECORD
